wings/__init__.py
wings/api_client.py
wings/component.py
wings/data.py
wings/domain.py
wings/execution.py
wings/planner.py
wings/resource.py
wings/user.py
wings_client-1.4.0.dist-info/LICENSE
wings_client-1.4.0.dist-info/METADATA
wings_client-1.4.0.dist-info/WHEEL
wings_client-1.4.0.dist-info/RECORD
